ks4r/__init__.py
ks4r/ks4r.py
ks4r-1.0.dist-info/LICENSE
ks4r-1.0.dist-info/METADATA
ks4r-1.0.dist-info/WHEEL
ks4r-1.0.dist-info/top_level.txt
ks4r-1.0.dist-info/RECORD
