Metadata-Version: 2.1
Name: ks4r
Version: 1.0
Summary: for hangul review summarize based textrank, pagerank and bm25
Home-page: https://github.com/kadarin123/KoreanReviewSummarizer
Author: Team footfoot
Author-email: kadarin123@naver.com
License: UNKNOWN
Download-URL: https://github.com/kadarin123/KoreanReviewSummarizer/archive/master.zip
Keywords: text summarize,korean text,review summarize
Platform: UNKNOWN
Classifier: Programming Language :: Python :: 3
Classifier: Programming Language :: Python :: 3.2
Classifier: Programming Language :: Python :: 3.3
Classifier: Programming Language :: Python :: 3.4
Classifier: Programming Language :: Python :: 3.5
Classifier: Programming Language :: Python :: 3.6
Classifier: Programming Language :: Python :: 3.7
Classifier: Programming Language :: Python :: 3.8
Requires-Python: >=3
Requires-Dist: numpy
Requires-Dist: requests
Requires-Dist: rank-bm25
Requires-Dist: konlpy
Requires-Dist: networkx
